gwozai_wechat_bot/__init__.py
gwozai_wechat_bot/bot.py
gwozai_wechat_bot-2.0.0.dist-info/licenses/LICENSE
gwozai_wechat_bot-2.0.0.dist-info/METADATA
gwozai_wechat_bot-2.0.0.dist-info/WHEEL
gwozai_wechat_bot-2.0.0.dist-info/top_level.txt
gwozai_wechat_bot-2.0.0.dist-info/RECORD
