Metadata-Version: 2.4
Name: gwozai-wechat-bot
Version: 2.0.0
Summary: 企业微信群机器人 Python SDK，支持所有消息类型、自动重试、异步发送、消息模板
Home-page: https://github.com/gwozai/gwozai-wechat-bot
Author: gwozai
Author-email: gwozai <gwozai@example.com>
License: MIT
Project-URL: Homepage, https://github.com/gwozai/gwozai-wechat-bot
Project-URL: Documentation, https://github.com/gwozai/gwozai-wechat-bot#readme
Project-URL: Repository, https://github.com/gwozai/gwozai-wechat-bot
Project-URL: Issues, https://github.com/gwozai/gwozai-wechat-bot/issues
Keywords: wechat,wecom,企业微信,机器人,webhook,bot,gwozai
Classifier: Development Status :: 5 - Production/Stable
Classifier: Intended Audience :: Developers
Classifier: License :: OSI Approved :: MIT License
Classifier: Operating System :: OS Independent
Classifier: Programming Language :: Python :: 3
Classifier: Programming Language :: Python :: 3.8
Classifier: Programming Language :: Python :: 3.9
Classifier: Programming Language :: Python :: 3.10
Classifier: Programming Language :: Python :: 3.11
Classifier: Programming Language :: Python :: 3.12
Classifier: Topic :: Communications :: Chat
Classifier: Topic :: Software Development :: Libraries :: Python Modules
Requires-Python: >=3.8
License-File: LICENSE
Requires-Dist: requests>=2.20.0
Provides-Extra: dotenv
Requires-Dist: python-dotenv>=0.19.0; extra == "dotenv"
Provides-Extra: all
Requires-Dist: python-dotenv>=0.19.0; extra == "all"
Provides-Extra: dev
Requires-Dist: python-dotenv>=0.19.0; extra == "dev"
Requires-Dist: pytest>=7.0.0; extra == "dev"
Requires-Dist: pytest-asyncio>=0.20.0; extra == "dev"
Dynamic: license-file
